appscii/__init__.py
appscii/__main__.py
appscii/__version__.py
appscii/app.py
appscii/helper.py
appscii/win.py
appscii/backend/__init__.py
appscii/backend/common.py
appscii/backend/curses.py
appscii/backend/matrix.py
appscii/backend/win32.py
appscii/font/__init__.py
appscii/font/big.py
appscii/font/big_only_caps.py
appscii-0.1.3.dist-info/LICENSE
appscii-0.1.3.dist-info/METADATA
appscii-0.1.3.dist-info/WHEEL
appscii-0.1.3.dist-info/entry_points.txt
appscii-0.1.3.dist-info/top_level.txt
appscii-0.1.3.dist-info/RECORD
