Metadata-Version: 2.1
Name: appscii
Version: 0.1.3
Summary: Application in ASCII
Home-page: https://github.com/lannocc/appscii
Author: LANNOCC (Shawn A. Wilson)
Author-email: lannocc@yahoo.com
Classifier: Programming Language :: Python :: 3
Classifier: License :: OSI Approved :: MIT License
Classifier: Operating System :: OS Independent
License-File: LICENSE
Requires-Dist: pywin32 ; platform_system == "Windows"
